{
  "2": [
    {
      "name": "Φυσικός Χυμός",
      "price": 5,
      "category": "Χυμοί",
      "coffeePreference": null,
      "coffeeSize": null,
      "extras": null,
      "printer": "bar",
      "id": "65ca05cb-a91e-4eeb-8374-3c3ab38a5f60",
      "printed": true,
      "timestamp": "02/12/2025 20:45:04"
    },
    {
      "name": "Κρέπα γλυκιά",
      "price": 5,
      "category": "Τοστ - Κρέπες",
      "coffeePreference": null,
      "coffeeSize": null,
      "extras": [
        {
          "name": "Μερέντα",
          "price": 0.5
        },
        {
          "name": "Bueno Κομματάκια",
          "price": 1
        }
      ],
      "materialsSweet": true,
      "printer": "crepe",
      "id": "8e550568-4ae4-4493-a067-30f1e4791f04",
      "printed": true,
      "timestamp": "02/12/2025 20:45:14"
    }
  ],
  "13": [
    {
      "name": "Ποτό Σπέσιαλ",
      "price": 8,
      "category": "Ποτά - Κρασιά",
      "coffeePreference": null,
      "coffeeSize": null,
      "extras": null,
      "printer": "bar",
      "comments": "μπιφιτερ Πινκ ",
      "id": "77116096-2c83-44c2-9008-c44205bf09d0",
      "printed": true,
      "timestamp": "02/12/2025 21:26:17"
    },
    {
      "name": "Κρασί ποτήρι",
      "price": 6,
      "category": "Ποτά - Κρασιά",
      "coffeePreference": null,
      "coffeeSize": null,
      "extras": null,
      "printer": "bar",
      "comments": "παράγκα ",
      "id": "ad778a7b-e40e-4509-b1d7-9e83360fccf5",
      "printed": true,
      "timestamp": "02/12/2025 21:26:22"
    },
    {
      "name": "Κρέπα αλμυρή",
      "price": 5,
      "category": "Τοστ - Κρέπες",
      "coffeePreference": null,
      "coffeeSize": null,
      "extras": [
        {
          "name": "κασέρι",
          "price": 0.5
        },
        {
          "name": "ζαμπόν",
          "price": 0.5
        },
        {
          "name": "μπέικον",
          "price": 0.5
        },
        {
          "name": "μανιτάρια",
          "price": 0.5
        }
      ],
      "materials": true,
      "printer": "crepe",
      "comments": "τυροσαλατα 2πλο κασέρι κομμένη ",
      "id": "b16ab780-d653-4ea6-a792-2020cb8b166e",
      "printed": true,
      "timestamp": "02/12/2025 21:30:59"
    },
    {
      "name": "Σαλάτα Caesar",
      "price": 8.5,
      "category": "Σαλάτες",
      "coffeePreference": null,
      "coffeeSize": null,
      "extras": null,
      "printer": "kitchen",
      "comments": "πολύ κοτόπουλο ",
      "id": "dd0d8de6-b870-4256-a2e1-8ed67c531b74",
      "printed": true,
      "timestamp": "02/12/2025 21:33:47"
    },
    {
      "name": "Ποτό Σπέσιαλ",
      "price": 8,
      "category": "Ποτά - Κρασιά",
      "coffeePreference": null,
      "coffeeSize": null,
      "extras": null,
      "printer": "bar",
      "comments": "μπιφιτερ Πινκ ",
      "id": "6ffed85c-5925-4ed3-aa03-7fc09ef40a51",
      "printed": true,
      "timestamp": "02/12/2025 21:56:12"
    }
  ]
}